tati_tools/__init__.py
tati_tools/data_processing/__init__.py
tati_tools/data_processing/boxes_helpers.py
tati_tools/data_processing/image_helpers.py
tati_tools/dl/__init__.py
tati_tools/dl/losses/__init__.py
tati_tools/dl/losses/bce_jaccard.py
tati_tools/dl/losses/dice.py
tati_tools/dl/losses/jaccard.py
tati_tools/dl/metrics/__init__.py
tati_tools/dl/metrics/iou.py
tati_tools/dl/models_tools/__init__.py
tati_tools/dl/models_tools/model_helpers.py
tati_tools/dl/transforms/__init__.py
tati_tools-0.0.3.dist-info/METADATA
tati_tools-0.0.3.dist-info/WHEEL
tati_tools-0.0.3.dist-info/top_level.txt
tati_tools-0.0.3.dist-info/RECORD
